hatch_aws/__init__.py
hatch_aws/aws.py
hatch_aws/builder.py
hatch_aws/config.py
hatch_aws/hooks.py
hatch_aws-1.1.0.dist-info/METADATA
hatch_aws-1.1.0.dist-info/WHEEL
hatch_aws-1.1.0.dist-info/entry_points.txt
hatch_aws-1.1.0.dist-info/licenses/LICENSE.txt
hatch_aws-1.1.0.dist-info/RECORD
