Metadata-Version: 2.1
Name: hatch-aws
Version: 1.1.0
Summary: Hatch plugin for building AWS Lambda functions with SAM
Project-URL: Documentation, https://github.com/aka-raccoon/hatch-aws#readme
Project-URL: Issues, https://github.com/aka-raccoon/hatch-aws/issues
Project-URL: Source, https://github.com/aka-raccoon/hatch-aws
Author-email: aka-raccoon <aka-raccoon@pm.me>
License: MIT License
License-File: LICENSE.txt
Keywords: aws,hatch,lambda,plugin,sam
Classifier: Framework :: Hatch
Classifier: Programming Language :: Python
Classifier: Programming Language :: Python :: 3.8
Classifier: Programming Language :: Python :: 3.9
Classifier: Programming Language :: Python :: 3.10
Classifier: Programming Language :: Python :: 3.11
Classifier: Programming Language :: Python :: Implementation :: CPython
Classifier: Programming Language :: Python :: Implementation :: PyPy
Requires-Python: >=3.8
Requires-Dist: hatchling
Requires-Dist: pyyaml
Provides-Extra: dev
Requires-Dist: bandit[toml]; extra == 'dev'
Requires-Dist: black; extra == 'dev'
Requires-Dist: isort; extra == 'dev'
Requires-Dist: mypy; extra == 'dev'
Requires-Dist: pylint; extra == 'dev'
Requires-Dist: types-pyyaml; extra == 'dev'
Provides-Extra: test
Requires-Dist: coverage; extra == 'test'
Requires-Dist: pytest; extra == 'test'
Requires-Dist: pytest-cov; extra == 'test'
Requires-Dist: pytest-mock; extra == 'test'
Requires-Dist: tomli-w; extra == 'test'
